kocrawl/__init__.py
kocrawl/base.py
kocrawl/config.py
kocrawl/daum_dict.py
kocrawl/daum_news.py
kocrawl/decorators.py
kocrawl/dust.py
kocrawl/eco_activity.py
kocrawl/map.py
kocrawl/rent.py
kocrawl/spell.py
kocrawl/term.py
kocrawl/weather.py
kocrawl/answerer/__init__.py
kocrawl/answerer/base_answerer.py
kocrawl/answerer/dust_answerer.py
kocrawl/answerer/eco_answerer.py
kocrawl/answerer/map_answerer.py
kocrawl/answerer/rent_answerer.py
kocrawl/answerer/term_answerer.py
kocrawl/answerer/weather_answerer.py
kocrawl/editor/__init__.py
kocrawl/editor/base_editor.py
kocrawl/editor/dust_editor.py
kocrawl/editor/map_editor.py
kocrawl/editor/rent_editor.py
kocrawl/editor/term_editor.py
kocrawl/editor/weather_editor.py
kocrawl/searcher/__init__.py
kocrawl/searcher/base_searcher.py
kocrawl/searcher/daum_dict_searcher.py
kocrawl/searcher/daum_news_searcher.py
kocrawl/searcher/dust_searcher.py
kocrawl/searcher/eco_searcher.py
kocrawl/searcher/map_searcher.py
kocrawl/searcher/rent_searcher.py
kocrawl/searcher/term_searcher.py
kocrawl/searcher/weather_searcher.py
tests/__init__.py
tests/test_daum_dict.py
tests/test_daum_news.py
tests/test_dust.py
tests/test_eco.py
tests/test_map.py
tests/test_rent.py
tests/test_spell.py
tests/test_term.py
tests/test_weatherl.py
kocrawl_cna-1.0.1.dist-info/LICENSE
kocrawl_cna-1.0.1.dist-info/METADATA
kocrawl_cna-1.0.1.dist-info/WHEEL
kocrawl_cna-1.0.1.dist-info/top_level.txt
kocrawl_cna-1.0.1.dist-info/RECORD
