Metadata-Version: 2.1
Name: kocrawl-cna
Version: 1.0.1
Summary: Korean web crawler collections
Home-page: https://github.com/choyoungeun/kocrawl-cna.git
Author: (original : Hyunwoong Ko), Saebom Lee, Jeongyun Seo, Youngeun Cho
Author-email: gusdnd852@naver.com
License: UNKNOWN
Keywords: crawler,korean crawler,kochat
Platform: UNKNOWN
Classifier: Programming Language :: Python :: 3
Classifier: Programming Language :: Python :: 3.2
Classifier: Programming Language :: Python :: 3.3
Classifier: Programming Language :: Python :: 3.4
Classifier: Programming Language :: Python :: 3.5
Classifier: Programming Language :: Python :: 3.6
Classifier: Programming Language :: Python :: 3.7
Classifier: Programming Language :: Python :: 3.8
Classifier: Programming Language :: Python :: 3.9
Requires-Python: >=3
License-File: LICENSE
Requires-Dist: numpy (==1.18.5)
Requires-Dist: beautifulsoup4 (==4.6.0)
Requires-Dist: requests (==2.24.0)
Requires-Dist: tqdm
